<?xml version="1.0"?>
<fm-container xmlns:xs="http://www.w3.org/2001/XMLSchema" xmlns:xsi="http://www.w3.org/2001/XMLSchema-instance" xsi:schemaLocation="http://www.hp.com/schemas/imaging/con/raster-data/devices-family/2009/08/21/&#10;                Schemas/family.xsd"><family name="copperhead12" link="Families/Copperhead.xml#/fm-container/family[@name='copperhead']"><capabilities link="Families/Copperhead.xml#/fm-container/family[@name='copperhead']/capabilities"><media-size-pick link="Families/Copperhead.xml#/fm-container/family[@name='copperhead']/capabilities/media-size-pick"><media-size name="iso-a4-duplexsafe" link="Data/Data.xml#/data-container/media-size-definitions/media-size[@name='iso-a4-duplexsafe']"><extra-skip-info name="TLES" link="$printer-root#.//capabilities/extra-skip-info"/></media-size><media-size name="na-letter-duplexsafe" link="Data/Data.xml#/data-container/media-size-definitions/media-size[@name='na-letter-duplexsafe']"><extra-skip-info name="TLES" link="$printer-root#.//capabilities/extra-skip-info"/></media-size></media-size-pick><media-type-pick link="Families/Copperhead.xml#/fm-container/family[@name='copperhead']/capabilities/media-type-pick"><media-type name="hp-premium-plus-photo-paper" link="Families/Copperhead.xml#/fm-container/family[@name='copperhead']/capabilities/media-type-pick/media-type[@name='hp-premium-plus-photo-paper']"><media-type-info link="Families/Copperhead.xml#/fm-container/family[@name='copperhead']/capabilities/media-type-pick/media-type[@name='hp-premium-plus-photo-paper']/media-type-info" pcl-media-type="5" vip-pcl-sub-Type="0"/><print-quality-pick link="$printer-root#./capabilities/print-qualities" default="normal"/></media-type><media-type name="plain-hagaki" link="Families/Copperhead.xml#/fm-container/family[@name='copperhead']/capabilities/media-type-pick/media-type[@name='plain-hagaki']"><media-type-info link="Families/Copperhead.xml#/fm-container/family[@name='copperhead']/capabilities/media-type-pick/media-type[@name='plain-hagaki']/media-type-info" pcl-media-type="2"/><print-quality-pick link="$printer-root#./capabilities/print-qualities" default="normal"><print-quality name="high-speed-draft" used="false"/><print-quality name="highest" used="false"/></print-quality-pick></media-type></media-type-pick></capabilities><ppd link="Families/Copperhead.xml#/fm-container/family[@name='copperhead']/ppd"><constraints link="Families/Copperhead.xml#/fm-container/family[@name='copperhead']/ppd/constraints"><constraint name="duplex-tumble-page-size-constraint" link="Families/Copperhead.xml#/fm-container/family[@name='copperhead']/ppd/constraints/constraint[@name='duplex-tumble-page-size-constraint']" cupsUIConstraint="true"/><constraint name="duplex-tumble-page-region-constraint" link="Families/Copperhead.xml#/fm-container/family[@name='copperhead']/ppd/constraints/constraint[@name='duplex-tumble-page-region-constraint']" cupsUIConstraint="true"/><constraint name="duplex-tumble-paper-type-constraint" link="Families/Copperhead.xml#/fm-container/family[@name='copperhead']/ppd/constraints/constraint[@name='duplex-tumble-paper-type-constraint']" cupsUIConstraint="true"><resolver>DuplexPaperTypeDefaultResolver</resolver></constraint><constraint name="duplex-a4-duplexsafe-page-size-constraint" cupsUIConstraint="true"><option-id name="option-1">Duplex</option-id><option-id name="option-2">PageSize</option-id><choice-id name="choice-2">A4</choice-id><resolver>A4DuplexSafeSizeResolver</resolver></constraint><constraint name="duplex-letter-duplexsafe-page-size-constraint" cupsUIConstraint="true"><option-id name="option-1">Duplex</option-id><option-id name="option-2">PageSize</option-id><choice-id name="choice-2">Letter</choice-id><resolver>LetterDuplexSafeSizeResolver</resolver></constraint><constraint name="duplex-a4-duplexsafe-page-region-constraint" cupsUIConstraint="true"><option-id name="option-1">Duplex</option-id><option-id name="option-2">PageRegion</option-id><choice-id name="choice-2">A4</choice-id><resolver>A4DuplexSafeRegionResolver</resolver></constraint><constraint name="duplex-letter-duplexsafe-page-region-constraint" cupsUIConstraint="true"><option-id name="option-1">Duplex</option-id><option-id name="option-2">PageRegion</option-id><choice-id name="choice-2">Letter</choice-id><resolver>LetterDuplexSafeRegionResolver</resolver></constraint></constraints><printer-presets link="Families/Copperhead.xml#/fm-container/family[@name='copperhead']/ppd/printer-presets"><printer-preset name="Plain_paper_Fast_Draft" link="Data/PresetsData.xml#/presets-container//printer-preset[@name='Plain_paper_Fast_Draft']"><value link="Data/PresetsData.xml#/presets-container//preset[@preset-type='general'][@name='plain-paper-high-speed-draft-main-tray']"/></printer-preset><printer-preset name="Plain_paper_Fast_Draft_Black_and_White" link="Data/PresetsData.xml#/presets-container//printer-preset[@name='Plain_paper_Fast_Draft_Black_and_White']"><value link="Data/PresetsData.xml#/presets-container//preset[@preset-type='general'][@name='plain-paper-high-speed-draft-grayscale-black-only-main-tray']"/></printer-preset><printer-preset name="Plain_paper_Best" link="Data/PresetsData.xml#/presets-container//printer-preset[@name='Plain_paper_Best']"><value link="Data/PresetsData.xml#/presets-container//preset[@preset-type='general'][@name='plain-paper-best-main-tray']"/></printer-preset><printer-preset name="Photo_paper" link="Data/PresetsData.xml#/presets-container//printer-preset[@name='Photo_paper']"><value link="Data/PresetsData.xml#/presets-container//preset[@preset-type='general'][@name='hp-advanced-photo-paper-glossy-normal-main-tray']"/></printer-preset></printer-presets><constraint-resolvers><resolver name="A4DuplexSafeSizeResolver"><option-id name="option-1">PageSize</option-id><option-id name="option-2">Duplex</option-id><choice-id name="choice-1">A4.DuplexSafe</choice-id><choice-id name="choice-2">None</choice-id><comment>CUPS UI constraints resolvers</comment></resolver><resolver name="LetterDuplexSafeSizeResolver"><option-id name="option-1">PageSize</option-id><option-id name="option-2">Duplex</option-id><choice-id name="choice-1">Letter.DuplexSafe</choice-id><choice-id name="choice-2">None</choice-id></resolver><resolver name="A4DuplexSafeRegionResolver"><option-id name="option-1">PageRegion</option-id><option-id name="option-2">Duplex</option-id><choice-id name="choice-1">A4.DuplexSafe</choice-id><choice-id name="choice-2">None</choice-id></resolver><resolver name="LetterDuplexSafeRegionResolver"><option-id name="option-1">PageRegion</option-id><option-id name="option-2">Duplex</option-id><choice-id name="choice-1">Letter.DuplexSafe</choice-id><choice-id name="choice-2">None</choice-id></resolver><resolver name="DuplexPaperTypeDefaultResolver"><option-id name="option-1">Duplex</option-id><option-id name="option-2">MediaType</option-id><choice-id name="choice-1">None</choice-id></resolver></constraint-resolvers></ppd><product link="Families/Copperhead.xml#/fm-container/family[@name='copperhead']/product"><features link="Families/Copperhead.xml#/fm-container/family[@name='copperhead']/product/features"><feature name="supports-auto-duplex" link="Families/Copperhead.xml#/fm-container/family[@name='copperhead']/product/features/feature[@name='supports-auto-duplex']">true</feature><feature name="supports-drytime" used="false"/></features></product></family></fm-container>
